{
  "type": "Feature",
  "properties": {
    "iso:country":"GR",
    "sg:address":"20-22 Ypsilantou Str.",
    "sg:city":"Athens",
    "sg:classifiers":[
        {
            "category":"Professional",
            "subcategory":"Computer Services",
            "type":"Services"
        }
    ],
    "sg:postcode":"10676",
    "sg:tags":[
        "social-network",
        "site",
        "messaging",
        "texting",
        "mobile-network",
        "smart-phone"
    ],
    "sg:website":"http://us.wadja.com/home.aspx",
    "wof:name":"Wadja",
    "wof:placetype":"venue"
},
  "geometry": {"coordinates":[23.798241,38.05635],"type":"Point"}
}