{
  "type": "Feature",
  "properties": {
    "iso:country":"GR",
    "sg:address":"Meletiou Vasileiou 14-16 Str",
    "sg:city":"Athens",
    "sg:classifiers":[
        {
            "category":"Professional",
            "subcategory":"Computer Services",
            "type":"Services"
        }
    ],
    "sg:postcode":"11745",
    "sg:tags":[
        "prediction-markets",
        "information-markets",
        "virtual-markets",
        "dynamic-surveys",
        "intra-enterprise",
        "predictions",
        "aggregation",
        "decision-support",
        "bet",
        "game"
    ],
    "sg:website":"http://www.askmarkets.com",
    "wof:name":"askmarkets",
    "wof:placetype":"venue"
},
  "geometry": {"coordinates":[23.706248,38.044896],"type":"Point"}
}