{
  "type": "Feature",
  "properties": {
    "iso:country":"GR",
    "sg:address":"75  Artoxinou",
    "sg:city":"Athens",
    "sg:classifiers":[
        {
            "category":"Professional",
            "subcategory":"Management & Consulting",
            "type":"Services"
        }
    ],
    "sg:postcode":"12135",
    "sg:website":"http://www.technodyne.gr",
    "wof:name":"Technodyne ",
    "wof:placetype":"venue"
},
  "geometry": {"coordinates":[23.6879859,38.0248447],"type":"Point"}
}