{
  "type": "Feature",
  "properties": {
    "iso:country":"GR",
    "sg:address":"Asimaki Fotila 28",
    "sg:city":"Athens",
    "sg:classifiers":[
        {
            "category":"Professional",
            "subcategory":"Computer Services",
            "type":"Services"
        }
    ],
    "sg:postcode":"11473",
    "sg:tags":[
        "accommodation",
        "web-service",
        "mapvertising",
        "community"
    ],
    "sg:website":"http://www.stayinathens.com",
    "wof:name":"StayInAthens",
    "wof:placetype":"venue"
},
  "geometry": {"coordinates":[23.737131,37.990428],"type":"Point"}
}